LICENSE
MANIFEST.in
README.rst
pyproject.toml
setup.cfg
setup.py
klink/__init__.py
klink/demo.py
klink/layout.html
klink/theme.conf
klink.egg-info/PKG-INFO
klink.egg-info/SOURCES.txt
klink.egg-info/dependency_links.txt
klink.egg-info/requires.txt
klink.egg-info/top_level.txt
klink/__pycache__/__init__.cpython-311.pyc
klink/__pycache__/demo.cpython-311.pyc
klink/less/klink.less
klink/less/vendor/3L.less
klink/less/vendor/font-awesome/fonts/FontAwesome.otf
klink/less/vendor/font-awesome/fonts/fontawesome-webfont.eot
klink/less/vendor/font-awesome/fonts/fontawesome-webfont.svg
klink/less/vendor/font-awesome/fonts/fontawesome-webfont.ttf
klink/less/vendor/font-awesome/fonts/fontawesome-webfont.woff
klink/less/vendor/font-awesome/less/bordered-pulled.less
klink/less/vendor/font-awesome/less/core.less
klink/less/vendor/font-awesome/less/extras.less
klink/less/vendor/font-awesome/less/fixed-width.less
klink/less/vendor/font-awesome/less/font-awesome.less
klink/less/vendor/font-awesome/less/icons.less
klink/less/vendor/font-awesome/less/larger.less
klink/less/vendor/font-awesome/less/list.less
klink/less/vendor/font-awesome/less/mixins.less
klink/less/vendor/font-awesome/less/path.less
klink/less/vendor/font-awesome/less/rotated-flipped.less
klink/less/vendor/font-awesome/less/spinning.less
klink/less/vendor/font-awesome/less/stacked.less
klink/less/vendor/font-awesome/less/variables.less
klink/static/css/klink.css
klink/static/fonts/FontAwesome.otf
klink/static/fonts/fontawesome-webfont.eot
klink/static/fonts/fontawesome-webfont.svg
klink/static/fonts/fontawesome-webfont.ttf
klink/static/fonts/fontawesome-webfont.woff
klink/static/img/favicon.ico
klink/static/img/logo.png