Metadata-Version: 2.1
Name: klink
Version: 0.1.10
Summary: Klink is a simple and clean theme for creating Sphinx docs, inspired by jrnl
Home-page: https://github.com/pmorissette/klink
Author: Philippe Morissette
Author-email: morissette.philippe@gmail.com
License: MIT
Classifier: Development Status :: 3 - Alpha
Classifier: Topic :: Software Development :: Libraries
Classifier: Programming Language :: Python
Requires-Python: >=3.7
License-File: LICENSE
Requires-Dist: sphinx
Provides-Extra: dev
Requires-Dist: isort<6,>=5; extra == "dev"
Requires-Dist: ruff<0.4,>=0.3; extra == "dev"
Requires-Dist: twine; extra == "dev"
Requires-Dist: wheel; extra == "dev"
